[
    {
        "submitDialogue": "\u55ef\uff0c\u5b8c\u6210\u7684\u4e0d\u9519", 
        "rewards": "3_5000|2_1_1_13|2_1_1_14", 
        "description": "\u6ca1\u6709\u5f3a\u5927\u7684\u5b9e\u529b\u662f\u4e0d\u80fd\u4eab\u53d7\u6e38\u620f\u7684\u4e50\u8da3\u6ef4\uff0c\u4f60\u5988\u53eb\u4f60\u5feb\u53bb\u5347\u7ea7\u4e86", 
        "chain": 1, 
        "maxLevel": 999, 
        "acceptNpc": 1, 
        "acceptDialogue": "\u7ec8\u4e8e\u89c1\u5230\u4f60\u4e86\uff0c\u6709\u4e8b\u9700\u8981\u4f60\u5e2e\u5fd9", 
        "minLevel": 1, 
        "questItems": "", 
        "cancel": false, 
        "job": 0, 
        "completeNpc": 1, 
        "unCompleteDialogue": "\u4f60\u7684\u4efb\u52a1\u8fd8\u6ca1\u5b8c\u6210", 
        "nextId": 10, 
        "type": 1, 
        "id": 1, 
        "condition": "5_10_1", 
        "name": "\u5feb\u53bb\u5347\u7ea7\u5427"
    }, 
    {
        "submitDialogue": "\u55ef\uff0c\u5b8c\u6210\u7684\u4e0d\u9519", 
        "rewards": "1_10_1_11|3_5000|2_1_1_13", 
        "description": "\u90a3\u4e2a\u5b64\u72ec\u7684\u8001\u4eba\u5e0c\u671b\u6709\u4eba\u966a\u5979\u804a\u5929", 
        "chain": 1, 
        "maxLevel": 999, 
        "acceptNpc": 2, 
        "acceptDialogue": "\u7ec8\u4e8e\u89c1\u5230\u4f60\u4e86\uff0c\u6709\u4e8b\u9700\u8981\u4f60\u5e2e\u5fd9", 
        "minLevel": 1, 
        "questItems": "", 
        "cancel": false, 
        "job": 0, 
        "completeNpc": 2, 
        "unCompleteDialogue": "\u4f60\u7684\u4efb\u52a1\u8fd8\u6ca1\u5b8c\u6210", 
        "nextId": 3, 
        "type": 2, 
        "id": 2, 
        "condition": "6_3_1", 
        "name": "\u548cNPC2\u53f7\u804a\u804a"
    }, 
    {
        "submitDialogue": "\u55ef\uff0c\u5b8c\u6210\u7684\u4e0d\u9519", 
        "rewards": "6_200|3_7000", 
        "description": "\u526f\u672c2\u4e2d\u5b58\u5728\u67d0\u79cd\u90aa\u6076\u7684\u6c14\u606f\uff0c\u6751\u957f\u5e0c\u671b\u4f60\u80fd\u627e\u51fa\u6839\u6e90", 
        "chain": 1, 
        "maxLevel": 999, 
        "acceptNpc": 2, 
        "acceptDialogue": "\u7ec8\u4e8e\u89c1\u5230\u4f60\u4e86\uff0c\u6709\u4e8b\u9700\u8981\u4f60\u5e2e\u5fd9", 
        "minLevel": 1, 
        "questItems": "", 
        "cancel": false, 
        "job": 0, 
        "completeNpc": 2, 
        "unCompleteDialogue": "\u4f60\u7684\u4efb\u52a1\u8fd8\u6ca1\u5b8c\u6210", 
        "nextId": 4, 
        "type": 2, 
        "id": 3, 
        "condition": "6_4_1", 
        "name": "\u901a\u5173\u526f\u672c2"
    }
]